gcp_helpers/__init__.py
gcp_helpers/cloud_tasks/__init__.py
gcp_helpers/cloud_tasks/manager.py
gcp_helpers/common/__init__.py
gcp_helpers/common/web.py
gcp_helpers/firestore/__init__.py
gcp_helpers/firestore/collections.py
gcp_helpers/functions/__init__.py
gcp_helpers/functions/decorators.py
gcp_helpers/functions/routers.py
gcp_ng_helpers-0.0.19.dist-info/LICENSE
gcp_ng_helpers-0.0.19.dist-info/METADATA
gcp_ng_helpers-0.0.19.dist-info/WHEEL
gcp_ng_helpers-0.0.19.dist-info/top_level.txt
gcp_ng_helpers-0.0.19.dist-info/RECORD
